khelpers/predepends.py
khelpers-1.0.2.dist-info/METADATA
khelpers-1.0.2.dist-info/WHEEL
khelpers-1.0.2.dist-info/licenses/LICENSE
khelpers-1.0.2.dist-info/RECORD
