Metadata-Version: 2.1
Name: khelpers
Version: 1.0.2
Summary: Helper Files
Author-email: Justin Kumpe <jakumpe@kumpes.com>
License-File: LICENSE
Classifier: License :: OSI Approved :: MIT License
Classifier: Operating System :: OS Independent
Classifier: Programming Language :: Python :: 3
Requires-Python: >=3.7
